[
  {
    "id": 5001,
    "subject": "창업관련법규",
    "page": 1,
    "type": "법규",
    "question": "중소기업창업지원법의 주된 목적은?",
    "choices": [
      "대기업 지원",
      "창업 촉진 및 성장 지원",
      "세금 징수",
      "수출 제한"
    ],
    "answer": 2,
    "explanation": "창업지원법은 창업 활성화와 성장 지원이 목적이다."
  },
  {
    "id": 5002,
    "subject": "창업관련법규",
    "page": 2,
    "type": "법규",
    "question": "창업자의 정의로 적절한 것은?",
    "choices": [
      "이미 사업 중인 자",
      "새로 사업을 시작하는 자",
      "공무원",
      "학생"
    ],
    "answer": 2,
    "explanation": "창업자는 새로운 사업을 시작하는 자를 의미한다."
  },
  {
    "id": 5003,
    "subject": "창업관련법규",
    "page": 3,
    "type": "법규",
    "question": "창업보육센터(BI)의 역할은?",
    "choices": [
      "세금 부과",
      "창업기업 지원 및 육성",
      "규제 강화",
      "사업 제한"
    ],
    "answer": 2,
    "explanation": "BI는 창업기업의 성장 지원을 수행한다."
  },
  {
    "id": 5004,
    "subject": "창업관련법규",
    "page": 4,
    "type": "법규",
    "question": "중소기업의 범위 기준은 주로 무엇에 의해 결정되는가?",
    "choices": [
      "대표자 나이",
      "매출 및 자산 규모",
      "직원 취미",
      "회사 위치"
    ],
    "answer": 2,
    "explanation": "중소기업 기준은 매출액, 자산, 종업원 수 등으로 결정된다."
  },
  {
    "id": 5005,
    "subject": "창업관련법규",
    "page": 5,
    "type": "법규",
    "question": "벤처기업 인증의 주요 목적은?",
    "choices": [
      "세금 증가",
      "기술 기반 기업 육성",
      "사업 제한",
      "수출 금지"
    ],
    "answer": 2,
    "explanation": "벤처기업 인증은 기술 혁신 기업을 지원하기 위함이다."
  },
  {
    "id": 5006,
    "subject": "창업관련법규",
    "page": 6,
    "type": "법규",
    "question": "창업기업 지원 정책의 핵심 방향은?",
    "choices": [
      "규제 강화",
      "자율성 및 성장 지원",
      "세금 증가",
      "사업 축소"
    ],
    "answer": 2,
    "explanation": "정부 정책은 창업 활성화를 목표로 한다."
  },
  {
    "id": 5007,
    "subject": "창업관련법규",
    "page": 7,
    "type": "법규",
    "question": "창업기업의 초기 지원 항목으로 적절한 것은?",
    "choices": [
      "벌금",
      "자금 및 공간 지원",
      "사업 제한",
      "세금 증가"
    ],
    "answer": 2,
    "explanation": "초기 기업에는 자금, 공간, 멘토링 지원이 이루어진다."
  },
  {
    "id": 5008,
    "subject": "창업관련법규",
    "page": 8,
    "type": "법규",
    "question": "기술창업의 특징으로 맞는 것은?",
    "choices": [
      "단순 판매",
      "기술 기반 사업",
      "세금 증가",
      "직원 감소"
    ],
    "answer": 2,
    "explanation": "기술창업은 기술을 기반으로 한다."
  },
  {
    "id": 5009,
    "subject": "창업관련법규",
    "page": 9,
    "type": "법규",
    "question": "정부 창업지원사업의 특징은?",
    "choices": [
      "무조건 지원",
      "평가 기반 선발",
      "세금 증가",
      "사업 제한"
    ],
    "answer": 2,
    "explanation": "정부사업은 평가를 통해 선발한다."
  },
  {
    "id": 5010,
    "subject": "창업관련법규",
    "page": 10,
    "type": "법규",
    "question": "창업보육센터 입주 조건으로 적절한 것은?",
    "choices": [
      "대기업",
      "창업 초기 기업",
      "공무원",
      "학생"
    ],
    "answer": 2,
    "explanation": "BI는 초기 창업기업을 대상으로 한다."
  },
  {
    "id": 5011,
    "subject": "창업관련법규",
    "page": 11,
    "type": "법규",
    "question": "보육기간의 일반적인 특징은?",
    "choices": [
      "무제한",
      "일정 기간 제한",
      "세금 증가",
      "사업 제한"
    ],
    "answer": 2,
    "explanation": "보육기간은 일정 기간으로 제한된다."
  },
  {
    "id": 5012,
    "subject": "창업관련법규",
    "page": 12,
    "type": "법규",
    "question": "창업기업 졸업 기준은?",
    "choices": [
      "임의 결정",
      "성장 및 성과 기준",
      "세금 증가",
      "사업 제한"
    ],
    "answer": 2,
    "explanation": "성과 기준에 따라 졸업 여부가 결정된다."
  },
  {
    "id": 5013,
    "subject": "창업관련법규",
    "page": 13,
    "type": "법규",
    "question": "창업지원법에서 지원 대상은?",
    "choices": [
      "대기업",
      "중소·창업기업",
      "공무원",
      "외국기업"
    ],
    "answer": 2,
    "explanation": "중소기업 및 창업기업이 주요 대상이다."
  },
  {
    "id": 5014,
    "subject": "창업관련법규",
    "page": 14,
    "type": "법규",
    "question": "창업기업의 의무로 적절한 것은?",
    "choices": [
      "무보고",
      "사업비 정산 및 보고",
      "세금 면제",
      "규제 없음"
    ],
    "answer": 2,
    "explanation": "지원금 사용 후 정산과 보고 의무가 있다."
  },
  {
    "id": 5015,
    "subject": "창업관련법규",
    "page": 15,
    "type": "법규",
    "question": "정부 지원금의 특징은?",
    "choices": [
      "자유 사용",
      "용도 제한",
      "세금 증가",
      "사업 제한"
    ],
    "answer": 2,
    "explanation": "지원금은 목적에 맞게 사용해야 한다."
  },
  {
    "id": 5016,
    "subject": "창업관련법규",
    "page": 16,
    "type": "법규",
    "question": "부정수급 시 조치로 적절한 것은?",
    "choices": [
      "추가 지원",
      "환수 및 제재",
      "세금 감소",
      "사업 확대"
    ],
    "answer": 2,
    "explanation": "부정수급은 환수 및 제재 대상이다."
  },
  {
    "id": 5017,
    "subject": "창업관련법규",
    "page": 17,
    "type": "법규",
    "question": "창업지원사업 참여 제한 사유는?",
    "choices": [
      "성실 수행",
      "부정행위",
      "정상 운영",
      "성과 우수"
    ],
    "answer": 2,
    "explanation": "부정행위는 참여 제한 사유다."
  },
  {
    "id": 5018,
    "subject": "창업관련법규",
    "page": 18,
    "type": "법규",
    "question": "협약 체결의 의미는?",
    "choices": [
      "비공식 약속",
      "법적 효력 있는 계약",
      "세금 증가",
      "사업 제한"
    ],
    "answer": 2,
    "explanation": "협약은 법적 효력을 가진다."
  },
  {
    "id": 5019,
    "subject": "창업관련법규",
    "page": 19,
    "type": "법규",
    "question": "사업비 집행 시 원칙은?",
    "choices": [
      "임의 사용",
      "지침 준수",
      "세금 증가",
      "사업 제한"
    ],
    "answer": 2,
    "explanation": "사업비는 지침에 따라 집행해야 한다."
  },
  {
    "id": 5020,
    "subject": "창업관련법규",
    "page": 20,
    "type": "정의",
    "question": "창업지원 정책의 최종 목적은?",
    "choices": [
      "세금 증가",
      "경제 활성화",
      "직원 감소",
      "사업 제한"
    ],
    "answer": 2,
    "explanation": "창업은 국가 경제 활성화와 직결된다."
  }
]
[
  {
    "id": 5021,
    "subject": "창업관련법규",
    "page": 21,
    "type": "법규",
    "question": "정부 창업지원사업에서 협약의 성격으로 가장 적절한 것은?",
    "choices": [
      "비공식 합의",
      "법적 효력 없는 문서",
      "법적 구속력을 가지는 계약",
      "내부 참고자료"
    ],
    "answer": 3,
    "explanation": "협약은 법적 효력을 가지며 사업 수행 기준이 된다."
  },
  {
    "id": 5022,
    "subject": "창업관련법규",
    "page": 22,
    "type": "법규",
    "question": "사업비 집행 시 증빙으로 인정되지 않는 것은?",
    "choices": [
      "세금계산서",
      "카드 영수증",
      "구두 확인",
      "계좌이체 내역"
    ],
    "answer": 3,
    "explanation": "구두 확인은 증빙으로 인정되지 않는다."
  },
  {
    "id": 5023,
    "subject": "창업관련법규",
    "page": 23,
    "type": "법규",
    "question": "부정수급에 해당하는 경우는?",
    "choices": [
      "지침 준수 사용",
      "정상 집행",
      "허위 증빙 제출",
      "계획 승인 후 집행"
    ],
    "answer": 3,
    "explanation": "허위 증빙은 대표적인 부정수급이다."
  },
  {
    "id": 5024,
    "subject": "창업관련법규",
    "page": 24,
    "type": "법규",
    "question": "사업비 변경 집행이 가능한 경우는?",
    "choices": [
      "임의 변경",
      "사전 승인 없이 변경",
      "승인 후 변경",
      "구두 보고 후 변경"
    ],
    "answer": 3,
    "explanation": "사업비 변경은 반드시 사전 승인 후 가능하다."
  },
  {
    "id": 5025,
    "subject": "창업관련법규",
    "page": 25,
    "type": "법규",
    "question": "참여 제한 조치가 가능한 사유는?",
    "choices": [
      "성과 우수",
      "정상 수행",
      "부정행위",
      "계획 준수"
    ],
    "answer": 3,
    "explanation": "부정행위는 참여 제한 사유이다."
  },
  {
    "id": 5026,
    "subject": "창업관련법규",
    "page": 26,
    "type": "법규",
    "question": "사업 수행 중 중대한 위반 발생 시 조치는?",
    "choices": [
      "추가 지원",
      "유예",
      "협약 해지",
      "보너스 지급"
    ],
    "answer": 3,
    "explanation": "중대한 위반 시 협약 해지 가능하다."
  },
  {
    "id": 5027,
    "subject": "창업관련법규",
    "page": 27,
    "type": "법규",
    "question": "정부지원금 환수 대상이 되는 경우는?",
    "choices": [
      "정상 집행",
      "성과 달성",
      "부정 사용",
      "계획 승인"
    ],
    "answer": 3,
    "explanation": "부정 사용 시 환수 대상이다."
  },
  {
    "id": 5028,
    "subject": "창업관련법규",
    "page": 28,
    "type": "법규",
    "question": "창업지원사업에서 정산의 목적은?",
    "choices": [
      "세금 증가",
      "비용 축소",
      "사업비 사용 검증",
      "지원 확대"
    ],
    "answer": 3,
    "explanation": "정산은 사업비 사용 적정성을 검증하는 것이다."
  },
  {
    "id": 5029,
    "subject": "창업관련법규",
    "page": 29,
    "type": "법규",
    "question": "사업비 집행 원칙으로 틀린 것은?",
    "choices": [
      "목적 외 사용 금지",
      "증빙 필수",
      "사전 승인 필요",
      "임의 전용 가능"
    ],
    "answer": 4,
    "explanation": "사업비는 임의 전용이 불가능하다."
  },
  {
    "id": 5030,
    "subject": "창업관련법규",
    "page": 30,
    "type": "법규",
    "question": "협약 종료 후 필수 절차는?",
    "choices": [
      "추가 집행",
      "사업 확장",
      "정산 및 보고",
      "재신청"
    ],
    "answer": 3,
    "explanation": "협약 종료 후 정산과 결과 보고가 필요하다."
  },
  {
    "id": 5031,
    "subject": "창업관련법규",
    "page": 31,
    "type": "법규",
    "question": "정부지원사업에서 성실 수행의 기준은?",
    "choices": [
      "임의 변경",
      "무보고",
      "계획 준수",
      "증빙 없음"
    ],
    "answer": 3,
    "explanation": "계획에 따라 성실히 수행해야 한다."
  },
  {
    "id": 5032,
    "subject": "창업관련법규",
    "page": 32,
    "type": "법규",
    "question": "사업 중단 시 필요한 조치는?",
    "choices": [
      "무보고",
      "임의 종료",
      "즉시 보고",
      "계속 집행"
    ],
    "answer": 3,
    "explanation": "사업 중단 시 즉시 보고해야 한다."
  },
  {
    "id": 5033,
    "subject": "창업관련법규",
    "page": 33,
    "type": "법규",
    "question": "사업비 부정 사용 시 가장 먼저 적용되는 조치는?",
    "choices": [
      "보상 지급",
      "추가 지원",
      "환수",
      "승진"
    ],
    "answer": 3,
    "explanation": "부정 사용은 우선 환수 조치 대상이다."
  },
  {
    "id": 5034,
    "subject": "창업관련법규",
    "page": 34,
    "type": "법규",
    "question": "사업 수행 기관의 역할은?",
    "choices": [
      "사업 방해",
      "감독 및 지원",
      "세금 징수",
      "사업 제한"
    ],
    "answer": 2,
    "explanation": "수행기관은 사업을 관리하고 지원한다."
  },
  {
    "id": 5035,
    "subject": "창업관련법규",
    "page": 35,
    "type": "법규",
    "question": "평가 결과에 따른 조치로 적절한 것은?",
    "choices": [
      "무조건 지원",
      "성과 기반 조치",
      "세금 증가",
      "사업 제한"
    ],
    "answer": 2,
    "explanation": "평가는 성과에 따라 지원 여부를 결정한다."
  },
  {
    "id": 5036,
    "subject": "창업관련법규",
    "page": 36,
    "type": "법규",
    "question": "사업비 집행 시 가장 중요한 원칙은?",
    "choices": [
      "속도",
      "정확성 및 적정성",
      "비용 증가",
      "임의 변경"
    ],
    "answer": 2,
    "explanation": "사업비는 정확하고 적정하게 집행해야 한다."
  },
  {
    "id": 5037,
    "subject": "창업관련법규",
    "page": 37,
    "type": "법규",
    "question": "정부지원사업의 평가 기준은?",
    "choices": [
      "감정",
      "객관적 기준",
      "무작위",
      "세금"
    ],
    "answer": 2,
    "explanation": "평가는 객관적인 기준으로 이루어진다."
  },
  {
    "id": 5038,
    "subject": "창업관련법규",
    "page": 38,
    "type": "법규",
    "question": "협약 위반 시 가능한 조치는?",
    "choices": [
      "추가 지원",
      "경고 및 제재",
      "보상",
      "확대"
    ],
    "answer": 2,
    "explanation": "협약 위반 시 제재가 가능하다."
  },
  {
    "id": 5039,
    "subject": "창업관련법규",
    "page": 39,
    "type": "법규",
    "question": "사업 수행 결과 보고의 목적은?",
    "choices": [
      "세금 증가",
      "성과 확인",
      "사업 축소",
      "지원 중단"
    ],
    "answer": 2,
    "explanation": "보고는 사업 성과를 확인하기 위한 것이다."
  },
  {
    "id": 5040,
    "subject": "창업관련법규",
    "page": 40,
    "type": "정의",
    "question": "창업지원사업 관리의 핵심은?",
    "choices": [
      "임의 운영",
      "지침 준수와 투명성",
      "세금 증가",
      "사업 제한"
    ],
    "answer": 2,
    "explanation": "사업 관리는 투명성과 규정 준수가 핵심이다."
  }
]
[
  {
    "id": 5041,
    "subject": "창업관련법규",
    "page": 41,
    "type": "법규",
    "question": "다음 중 사업비 집행 원칙으로 옳지 않은 것은?",
    "choices": [
      "목적 외 사용 금지",
      "증빙 자료 확보",
      "사전 승인 후 변경",
      "잔액 자유 사용 가능"
    ],
    "answer": 4,
    "explanation": "사업비 잔액은 자유 사용이 불가능하며 반납 또는 정산 대상이다."
  },
  {
    "id": 5042,
    "subject": "창업관련법규",
    "page": 42,
    "type": "법규",
    "question": "협약 변경이 필요한 상황에서 올바른 절차는?",
    "choices": [
      "사후 통보",
      "구두 승인",
      "사전 승인 후 변경",
      "임의 변경"
    ],
    "answer": 3,
    "explanation": "협약 변경은 반드시 사전 승인 후 진행해야 한다."
  },
  {
    "id": 5043,
    "subject": "창업관련법규",
    "page": 43,
    "type": "법규",
    "question": "부정수급으로 판단되지 않는 경우는?",
    "choices": [
      "허위 증빙 제출",
      "타 사업비와 혼용",
      "지침에 따른 집행",
      "목적 외 사용"
    ],
    "answer": 3,
    "explanation": "지침에 따른 정상 집행은 부정수급이 아니다."
  },
  {
    "id": 5044,
    "subject": "창업관련법규",
    "page": 44,
    "type": "법규",
    "question": "사업 수행 중 계획 대비 변경이 발생했을 때 가장 적절한 조치는?",
    "choices": [
      "그대로 진행",
      "사후 보고",
      "즉시 변경 승인 요청",
      "무시"
    ],
    "answer": 3,
    "explanation": "변경 사항은 즉시 승인 절차를 거쳐야 한다."
  },
  {
    "id": 5045,
    "subject": "창업관련법규",
    "page": 45,
    "type": "법규",
    "question": "사업비를 타 용도로 전용한 경우 조치는?",
    "choices": [
      "경고 없음",
      "문제 없음",
      "환수 및 제재",
      "추가 지원"
    ],
    "answer": 3,
    "explanation": "사업비 전용은 환수 및 제재 대상이다."
  },
  {
    "id": 5046,
    "subject": "창업관련법규",
    "page": 46,
    "type": "법규",
    "question": "다음 중 협약 해지 사유로 가장 적절한 것은?",
    "choices": [
      "정상 수행",
      "성과 우수",
      "중대한 위반",
      "계획 준수"
    ],
    "answer": 3,
    "explanation": "중대한 위반은 협약 해지 사유가 된다."
  },
  {
    "id": 5047,
    "subject": "창업관련법규",
    "page": 47,
    "type": "법규",
    "question": "사업비 집행 시 가장 우선 고려 사항은?",
    "choices": [
      "속도",
      "편의성",
      "지침 준수",
      "금액"
    ],
    "answer": 3,
    "explanation": "사업비는 반드시 지침에 따라 집행해야 한다."
  },
  {
    "id": 5048,
    "subject": "창업관련법규",
    "page": 48,
    "type": "법규",
    "question": "정산 과정에서 가장 중요한 것은?",
    "choices": [
      "속도",
      "간편성",
      "증빙 일치 여부",
      "금액 크기"
    ],
    "answer": 3,
    "explanation": "정산은 증빙과 집행 내역의 일치가 핵심이다."
  },
  {
    "id": 5049,
    "subject": "창업관련법규",
    "page": 49,
    "type": "법규",
    "question": "다음 중 참여 제한 사유로 옳은 것은?",
    "choices": [
      "성과 달성",
      "계획 준수",
      "부정행위",
      "정상 집행"
    ],
    "answer": 3,
    "explanation": "부정행위는 참여 제한 사유이다."
  },
  {
    "id": 5050,
    "subject": "창업관련법규",
    "page": 50,
    "type": "법규",
    "question": "사업비 증빙으로 인정되는 것은?",
    "choices": [
      "구두 설명",
      "메모",
      "세금계산서",
      "추정 금액"
    ],
    "answer": 3,
    "explanation": "세금계산서는 공식 증빙이다."
  },
  {
    "id": 5051,
    "subject": "창업관련법규",
    "page": 51,
    "type": "법규",
    "question": "사업 중단 시 가장 먼저 해야 할 조치는?",
    "choices": [
      "자체 종료",
      "무시",
      "즉시 보고",
      "계속 진행"
    ],
    "answer": 3,
    "explanation": "사업 중단은 즉시 보고해야 한다."
  },
  {
    "id": 5052,
    "subject": "창업관련법규",
    "page": 52,
    "type": "법규",
    "question": "사업비 집행 내역과 증빙이 불일치할 경우 조치는?",
    "choices": [
      "문제 없음",
      "그대로 인정",
      "부정 집행 처리",
      "추가 지원"
    ],
    "answer": 3,
    "explanation": "불일치는 부정 집행으로 판단될 수 있다."
  },
  {
    "id": 5053,
    "subject": "창업관련법규",
    "page": 53,
    "type": "법규",
    "question": "협약 기간 내 반드시 수행해야 하는 것은?",
    "choices": [
      "임의 활동",
      "개인 사업",
      "계획된 사업 수행",
      "외부 활동"
    ],
    "answer": 3,
    "explanation": "협약 기간 내에는 계획된 사업을 수행해야 한다."
  },
  {
    "id": 5054,
    "subject": "창업관련법규",
    "page": 54,
    "type": "법규",
    "question": "다음 중 잘못된 사업비 집행 사례는?",
    "choices": [
      "승인 후 집행",
      "증빙 확보",
      "목적 외 사용",
      "지침 준수"
    ],
    "answer": 3,
    "explanation": "목적 외 사용은 명백한 위반이다."
  },
  {
    "id": 5055,
    "subject": "창업관련법규",
    "page": 55,
    "type": "법규",
    "question": "성과 평가 결과가 미흡할 경우 가능한 조치는?",
    "choices": [
      "추가 지원",
      "보상 지급",
      "지원 중단",
      "확대 지원"
    ],
    "answer": 3,
    "explanation": "성과 미흡 시 지원이 중단될 수 있다."
  },
  {
    "id": 5056,
    "subject": "창업관련법규",
    "page": 56,
    "type": "법규",
    "question": "다음 중 올바른 사업비 집행 절차는?",
    "choices": [
      "집행 후 승인",
      "임의 집행",
      "승인 후 집행",
      "구두 보고 후 집행"
    ],
    "answer": 3,
    "explanation": "사업비는 승인 후 집행이 원칙이다."
  },
  {
    "id": 5057,
    "subject": "창업관련법규",
    "page": 57,
    "type": "법규",
    "question": "부정수급 적발 시 가장 먼저 이루어지는 것은?",
    "choices": [
      "보상",
      "추가 지원",
      "환수",
      "확대"
    ],
    "answer": 3,
    "explanation": "부정수급은 환수가 우선이다."
  },
  {
    "id": 5058,
    "subject": "창업관련법규",
    "page": 58,
    "type": "법규",
    "question": "사업 수행 기관의 주요 기능은?",
    "choices": [
      "방해",
      "세금 징수",
      "관리 및 지원",
      "사업 제한"
    ],
    "answer": 3,
    "explanation": "기관은 사업을 관리하고 지원한다."
  },
  {
    "id": 5059,
    "subject": "창업관련법규",
    "page": 59,
    "type": "법규",
    "question": "다음 중 법규 위반이 아닌 것은?",
    "choices": [
      "허위 증빙",
      "부정 사용",
      "지침 준수",
      "무단 변경"
    ],
    "answer": 3,
    "explanation": "지침 준수는 정상 행위이다."
  },
  {
    "id": 5060,
    "subject": "창업관련법규",
    "page": 60,
    "type": "정의",
    "question": "창업지원사업에서 가장 중요한 관리 요소는?",
    "choices": [
      "속도",
      "금액",
      "투명성과 준법성",
      "편의성"
    ],
    "answer": 3,
    "explanation": "법규에서는 투명성과 준법성이 핵심이다."
  }
]
[
  {
    "id": 5061,
    "subject": "창업관련법규",
    "page": 61,
    "type": "법규",
    "question": "사업비를 계획과 다르게 사용했으나 사후에 보고한 경우 처리로 가장 적절한 것은?",
    "choices": [
      "문제 없음",
      "정상 인정",
      "부정 집행 가능성",
      "추가 지원"
    ],
    "answer": 3,
    "explanation": "사전 승인 없이 변경된 집행은 부정 집행으로 판단될 수 있다."
  },
  {
    "id": 5062,
    "subject": "창업관련법규",
    "page": 62,
    "type": "법규",
    "question": "다음 중 사업비 집행 절차로 옳은 것은?",
    "choices": [
      "집행 → 승인 → 보고",
      "승인 → 집행 → 증빙",
      "집행 → 보고 → 승인",
      "보고 → 집행 → 승인"
    ],
    "answer": 2,
    "explanation": "사업비는 승인 후 집행하고 증빙을 남겨야 한다."
  },
  {
    "id": 5063,
    "subject": "창업관련법규",
    "page": 63,
    "type": "법규",
    "question": "사업비 일부를 개인 용도로 사용한 경우 조치는?",
    "choices": [
      "경고",
      "정상 처리",
      "환수 및 제재",
      "문제 없음"
    ],
    "answer": 3,
    "explanation": "개인 용도 사용은 명백한 부정수급이다."
  },
  {
    "id": 5064,
    "subject": "창업관련법규",
    "page": 64,
    "type": "법규",
    "question": "다음 중 협약 변경이 불필요한 경우는?",
    "choices": [
      "사업비 항목 변경",
      "예산 금액 변경",
      "경미한 일정 조정",
      "사업 목적 변경"
    ],
    "answer": 3,
    "explanation": "경미한 일정 조정은 일부 경우 승인 없이 가능할 수 있다."
  },
  {
    "id": 5065,
    "subject": "창업관련법규",
    "page": 65,
    "type": "법규",
    "question": "사업 수행 중 허위 보고가 적발된 경우 가장 적절한 조치는?",
    "choices": [
      "경고",
      "재보고",
      "환수 및 참여 제한",
      "추가 지원"
    ],
    "answer": 3,
    "explanation": "허위 보고는 중대한 위반으로 강한 제재 대상이다."
  },
  {
    "id": 5066,
    "subject": "창업관련법규",
    "page": 66,
    "type": "법규",
    "question": "사업비 사용 시 증빙이 일부 누락된 경우 판단은?",
    "choices": [
      "정상 처리",
      "문제 없음",
      "부적정 집행",
      "추가 지원"
    ],
    "answer": 3,
    "explanation": "증빙 누락은 부적정 집행으로 판단된다."
  },
  {
    "id": 5067,
    "subject": "창업관련법규",
    "page": 67,
    "type": "법규",
    "question": "사업 중단 후 보고를 하지 않은 경우 조치는?",
    "choices": [
      "문제 없음",
      "경고",
      "제재 가능",
      "추가 지원"
    ],
    "answer": 3,
    "explanation": "보고 의무 위반은 제재 사유가 된다."
  },
  {
    "id": 5068,
    "subject": "창업관련법규",
    "page": 68,
    "type": "법규",
    "question": "다음 중 사업비 집행 원칙 위반에 해당하지 않는 것은?",
    "choices": [
      "목적 외 사용",
      "허위 증빙",
      "지침 준수 집행",
      "사전 승인 없는 변경"
    ],
    "answer": 3,
    "explanation": "지침 준수 집행은 정상이다."
  },
  {
    "id": 5069,
    "subject": "창업관련법규",
    "page": 69,
    "type": "법규",
    "question": "협약 기간 종료 후 사업비를 추가 집행한 경우 조치는?",
    "choices": [
      "정상 처리",
      "인정 가능",
      "부정 집행",
      "추가 지원"
    ],
    "answer": 3,
    "explanation": "협약 종료 후 집행은 인정되지 않는다."
  },
  {
    "id": 5070,
    "subject": "창업관련법규",
    "page": 70,
    "type": "법규",
    "question": "사업비 집행 시 카드 사용 내역이 실제 구매와 다른 경우는?",
    "choices": [
      "문제 없음",
      "정상 처리",
      "부정 집행",
      "추가 지원"
    ],
    "answer": 3,
    "explanation": "증빙 불일치는 부정 집행이다."
  },
  {
    "id": 5071,
    "subject": "창업관련법규",
    "page": 71,
    "type": "법규",
    "question": "사업비 일부를 다른 정부사업에 중복 사용한 경우는?",
    "choices": [
      "정상",
      "허용",
      "부정수급",
      "문제 없음"
    ],
    "answer": 3,
    "explanation": "중복 사용은 부정수급이다."
  },
  {
    "id": 5072,
    "subject": "창업관련법규",
    "page": 72,
    "type": "법규",
    "question": "다음 중 정산 시 가장 중요한 기준은?",
    "choices": [
      "금액",
      "속도",
      "증빙 일치",
      "편의성"
    ],
    "answer": 3,
    "explanation": "정산은 증빙과 실제 사용의 일치가 핵심이다."
  },
  {
    "id": 5073,
    "subject": "창업관련법규",
    "page": 73,
    "type": "법규",
    "question": "사업 수행 중 일부 항목을 미이행한 경우 조치는?",
    "choices": [
      "문제 없음",
      "보상 지급",
      "평가 반영 및 감점",
      "추가 지원"
    ],
    "answer": 3,
    "explanation": "미이행은 평가에 반영된다."
  },
  {
    "id": 5074,
    "subject": "창업관련법규",
    "page": 74,
    "type": "법규",
    "question": "사업비 집행 시 가장 위험한 위반 유형은?",
    "choices": [
      "지연",
      "금액 오류",
      "허위 증빙",
      "보고 지연"
    ],
    "answer": 3,
    "explanation": "허위 증빙은 가장 강한 제재 대상이다."
  },
  {
    "id": 5075,
    "subject": "창업관련법규",
    "page": 75,
    "type": "법규",
    "question": "다음 중 제재 수준이 가장 높은 것은?",
    "choices": [
      "지연 보고",
      "경미한 오류",
      "허위 자료 제출",
      "일정 변경"
    ],
    "answer": 3,
    "explanation": "허위 자료는 중대한 위반이다."
  },
  {
    "id": 5076,
    "subject": "창업관련법규",
    "page": 76,
    "type": "법규",
    "question": "사업비를 승인 없이 타 항목으로 이동한 경우는?",
    "choices": [
      "허용",
      "문제 없음",
      "부정 집행",
      "정상 처리"
    ],
    "answer": 3,
    "explanation": "사전 승인 없는 전용은 부정이다."
  },
  {
    "id": 5077,
    "subject": "창업관련법규",
    "page": 77,
    "type": "법규",
    "question": "사업 수행 결과가 계획 대비 미달된 경우 조치는?",
    "choices": [
      "보상",
      "추가 지원",
      "평가 감점 또는 중단",
      "문제 없음"
    ],
    "answer": 3,
    "explanation": "성과 미달은 평가에 반영된다."
  },
  {
    "id": 5078,
    "subject": "창업관련법규",
    "page": 78,
    "type": "법규",
    "question": "사업비 집행 후 증빙을 사후 작성한 경우 판단은?",
    "choices": [
      "정상",
      "허용",
      "부적정 가능성",
      "문제 없음"
    ],
    "answer": 3,
    "explanation": "사후 증빙은 인정되지 않을 수 있다."
  },
  {
    "id": 5079,
    "subject": "창업관련법규",
    "page": 79,
    "type": "법규",
    "question": "다음 중 가장 적절한 사업 관리 방식은?",
    "choices": [
      "임의 운영",
      "경험 기반",
      "지침 기반 관리",
      "속도 중심"
    ],
    "answer": 3,
    "explanation": "사업은 지침에 따라 관리해야 한다."
  },
  {
    "id": 5080,
    "subject": "창업관련법규",
    "page": 80,
    "type": "정의",
    "question": "창업지원사업 법규의 핵심 원칙은?",
    "choices": [
      "속도",
      "금액",
      "투명성·정확성·준법성",
      "편의성"
    ],
    "answer": 3,
    "explanation": "법규의 핵심은 투명성과 준법이다."
  }
]
[
  {
    "id": 5081,
    "subject": "창업관련법규",
    "page": 81,
    "type": "법규",
    "question": "사업비를 승인 없이 변경 집행하고 사후 보고한 경우 가장 적절한 판단은?",
    "choices": [
      "정상 처리",
      "부분 인정",
      "부정 집행",
      "문제 없음"
    ],
    "answer": 3,
    "explanation": "사전 승인 없는 변경은 부정 집행이다."
  },
  {
    "id": 5082,
    "subject": "창업관련법규",
    "page": 82,
    "type": "법규",
    "question": "협약 종료일 이후 발생한 비용을 사업비로 처리한 경우는?",
    "choices": [
      "정상 인정",
      "부분 인정",
      "부정 집행",
      "추가 지원"
    ],
    "answer": 3,
    "explanation": "협약 종료 후 비용은 인정되지 않는다."
  },
  {
    "id": 5083,
    "subject": "창업관련법규",
    "page": 83,
    "type": "법규",
    "question": "다음 중 가장 중대한 위반에 해당하는 것은?",
    "choices": [
      "보고 지연",
      "일정 변경",
      "허위 증빙 제출",
      "경미한 오류"
    ],
    "answer": 3,
    "explanation": "허위 증빙은 가장 강한 제재 대상이다."
  },
  {
    "id": 5084,
    "subject": "창업관련법규",
    "page": 84,
    "type": "법규",
    "question": "사업비 일부를 개인 계좌로 이체 후 사용한 경우 조치는?",
    "choices": [
      "정상",
      "경고",
      "환수 및 참여 제한",
      "문제 없음"
    ],
    "answer": 3,
    "explanation": "개인 사용은 중대한 부정수급이다."
  },
  {
    "id": 5085,
    "subject": "창업관련법규",
    "page": 85,
    "type": "법규",
    "question": "다음 중 사업비 집행 원칙을 모두 충족한 것은?",
    "choices": [
      "사후 승인 후 집행",
      "증빙 없이 집행",
      "사전 승인 후 증빙 확보",
      "임의 집행"
    ],
    "answer": 3,
    "explanation": "사전 승인 + 증빙 확보가 핵심이다."
  },
  {
    "id": 5086,
    "subject": "창업관련법규",
    "page": 86,
    "type": "법규",
    "question": "사업비 집행 시 허위 거래처를 만든 경우 조치는?",
    "choices": [
      "경고",
      "정상 처리",
      "형사 처벌 가능",
      "문제 없음"
    ],
    "answer": 3,
    "explanation": "허위 거래는 형사 문제까지 이어질 수 있다."
  },
  {
    "id": 5087,
    "subject": "창업관련법규",
    "page": 87,
    "type": "법규",
    "question": "사업비를 타 정부사업과 중복 사용한 경우는?",
    "choices": [
      "허용",
      "정상",
      "부정수급",
      "문제 없음"
    ],
    "answer": 3,
    "explanation": "중복 지원은 명백한 위반이다."
  },
  {
    "id": 5088,
    "subject": "창업관련법규",
    "page": 88,
    "type": "법규",
    "question": "다음 중 가장 적절한 정산 방식은?",
    "choices": [
      "추정 금액 제출",
      "구두 설명",
      "증빙 기반 정산",
      "임의 계산"
    ],
    "answer": 3,
    "explanation": "정산은 반드시 증빙 기반이어야 한다."
  },
  {
    "id": 5089,
    "subject": "창업관련법규",
    "page": 89,
    "type": "법규",
    "question": "사업 수행 중 일부 내용을 미이행하고 보고하지 않은 경우는?",
    "choices": [
      "정상",
      "문제 없음",
      "제재 가능",
      "보상"
    ],
    "answer": 3,
    "explanation": "미이행 + 미보고는 제재 대상이다."
  },
  {
    "id": 5090,
    "subject": "창업관련법규",
    "page": 90,
    "type": "법규",
    "question": "사업비 집행 후 증빙을 조작한 경우 조치는?",
    "choices": [
      "경고",
      "정상 처리",
      "환수 및 강력 제재",
      "문제 없음"
    ],
    "answer": 3,
    "explanation": "증빙 조작은 가장 강한 제재 대상이다."
  },
  {
    "id": 5091,
    "subject": "창업관련법규",
    "page": 91,
    "type": "법규",
    "question": "사업비를 승인된 항목 내에서 사용했으나 증빙이 없는 경우는?",
    "choices": [
      "정상",
      "허용",
      "부적정 집행",
      "문제 없음"
    ],
    "answer": 3,
    "explanation": "증빙이 없으면 인정되지 않는다."
  },
  {
    "id": 5092,
    "subject": "창업관련법규",
    "page": 92,
    "type": "법규",
    "question": "다음 중 가장 올바른 사업 운영 방식은?",
    "choices": [
      "임의 운영",
      "속도 중심",
      "지침 준수 운영",
      "경험 기반"
    ],
    "answer": 3,
    "explanation": "사업은 지침을 기준으로 운영해야 한다."
  },
  {
    "id": 5093,
    "subject": "창업관련법규",
    "page": 93,
    "type": "법규",
    "question": "사업비 일부를 직원 개인 용도로 사용한 경우는?",
    "choices": [
      "정상",
      "경고",
      "부정수급",
      "문제 없음"
    ],
    "answer": 3,
    "explanation": "개인 사용은 명확한 부정수급이다."
  },
  {
    "id": 5094,
    "subject": "창업관련법규",
    "page": 94,
    "type": "법규",
    "question": "협약 내용과 다르게 사업을 수행한 경우는?",
    "choices": [
      "허용",
      "정상",
      "위반",
      "문제 없음"
    ],
    "answer": 3,
    "explanation": "협약과 다른 수행은 위반이다."
  },
  {
    "id": 5095,
    "subject": "창업관련법규",
    "page": 95,
    "type": "법규",
    "question": "사업 종료 후 정산을 하지 않은 경우는?",
    "choices": [
      "정상",
      "문제 없음",
      "제재 대상",
      "추가 지원"
    ],
    "answer": 3,
    "explanation": "정산 미이행은 제재 사유이다."
  },
  {
    "id": 5096,
    "subject": "창업관련법규",
    "page": 96,
    "type": "법규",
    "question": "사업비 일부를 현금으로 사용하고 증빙이 없는 경우는?",
    "choices": [
      "정상",
      "허용",
      "부정 또는 부적정",
      "문제 없음"
    ],
    "answer": 3,
    "explanation": "현금 사용 + 증빙 없음은 인정되지 않는다."
  },
  {
    "id": 5097,
    "subject": "창업관련법규",
    "page": 97,
    "type": "법규",
    "question": "사업비를 승인 없이 항목 간 이동한 경우는?",
    "choices": [
      "정상",
      "허용",
      "부정 집행",
      "문제 없음"
    ],
    "answer": 3,
    "explanation": "항목 간 전용은 사전 승인 필요하다."
  },
  {
    "id": 5098,
    "subject": "창업관련법규",
    "page": 98,
    "type": "법규",
    "question": "다음 중 가장 올바른 사업비 관리 방식은?",
    "choices": [
      "임의 사용",
      "경험 중심",
      "증빙 기반 관리",
      "속도 중심"
    ],
    "answer": 3,
    "explanation": "사업비는 증빙 기반으로 관리해야 한다."
  },
  {
    "id": 5099,
    "subject": "창업관련법규",
    "page": 99,
    "type": "법규",
    "question": "부정수급이 적발된 경우 기본 조치는?",
    "choices": [
      "보상",
      "추가 지원",
      "환수 및 제재",
      "문제 없음"
    ],
    "answer": 3,
    "explanation": "부정수급은 환수와 제재가 기본이다."
  },
  {
    "id": 5100,
    "subject": "창업관련법규",
    "page": 100,
    "type": "정의",
    "question": "창업지원사업 법규의 최종 핵심은?",
    "choices": [
      "속도",
      "금액",
      "투명성과 준법성 유지",
      "편의성"
    ],
    "answer": 3,
    "explanation": "모든 법규의 핵심은 투명성과 준법이다."
  }
]
